swARM_at/RAK3172.py
swARM_at/RAK4270.py
swARM_at/__init__.py
swARM_at/exceptions.py
swarm_at-0.0.4.dist-info/licenses/LICENCE.txt
test/__init__.py
test/conftest.py
test/test_rak3172.py
test/test_rak4270.py
test/mocking/__init__.py
test/mocking/serial.py
swarm_at-0.0.4.dist-info/METADATA
swarm_at-0.0.4.dist-info/WHEEL
swarm_at-0.0.4.dist-info/top_level.txt
swarm_at-0.0.4.dist-info/RECORD
