Metadata-Version: 2.4
Name: swARM_at
Version: 0.0.4
Summary: Une bibliothèque pour la communication avec des modules LoRa via des commandes AT.
Home-page: https://gitlab.com/Apocalypzer/swarm_at
Author: Joffrey Herard
Author-email: joffrey.herard@gmail.com
Keywords: LoRa AT command RAK3172
Classifier: Development Status :: 3 - Alpha
Classifier: Intended Audience :: Developers
Classifier: Programming Language :: Python :: 3 :: Only
Classifier: Operating System :: Unix
Classifier: Operating System :: MacOS :: MacOS X
Classifier: Operating System :: Microsoft :: Windows
Classifier: License :: OSI Approved :: MIT License
License-File: LICENCE.txt
Requires-Dist: pyserial>=3.4
Dynamic: author
Dynamic: author-email
Dynamic: classifier
Dynamic: description
Dynamic: description-content-type
Dynamic: home-page
Dynamic: keywords
Dynamic: license-file
Dynamic: requires-dist
Dynamic: summary
